{
 "app": "airplane_mode",
 "charts": [],
 "content": "[{\"id\":\"PnexJ29tPU\",\"type\":\"header\",\"data\":{\"text\":\"<span class=\\\"h4\\\">Airplane Mode</span>\",\"col\":12}},{\"id\":\"8C5Y_mWd8l\",\"type\":\"shortcut\",\"data\":{\"shortcut_name\":\"All Airlines\",\"col\":3}},{\"id\":\"gj0da1EVRV\",\"type\":\"shortcut\",\"data\":{\"shortcut_name\":\"All Airplanes\",\"col\":3}},{\"id\":\"IbSIwyDOtY\",\"type\":\"shortcut\",\"data\":{\"shortcut_name\":\"All Passengers\",\"col\":3}}]",
 "creation": "2025-06-06 14:47:21.837323",
 "custom_blocks": [],
 "docstatus": 0,
 "doctype": "Workspace",
 "for_user": "",
 "hide_custom": 0,
 "icon": "grid",
 "idx": 0,
 "indicator_color": "yellow",
 "is_hidden": 0,
 "label": "Airplane Mode",
 "link_type": "DocType",
 "links": [],
 "modified": "2025-06-06 14:51:16.336312",
 "modified_by": "Administrator",
 "module": "Airplane Mode",
 "name": "Airplane Mode",
 "number_cards": [],
 "owner": "Administrator",
 "parent_page": "",
 "public": 1,
 "quick_lists": [],
 "roles": [],
 "sequence_id": 21.0,
 "shortcuts": [
  {
   "color": "Grey",
   "doc_view": "List",
   "label": "All Airlines",
   "link_to": "Airline",
   "stats_filter": "[]",
   "type": "DocType"
  },
  {
   "color": "Grey",
   "doc_view": "List",
   "label": "All Airplanes",
   "link_to": "Airplane",
   "stats_filter": "[]",
   "type": "DocType"
  },
  {
   "color": "Grey",
   "doc_view": "List",
   "label": "All Passengers",
   "link_to": "Flight passenger",
   "stats_filter": "[]",
   "type": "DocType"
  }
 ],
 "title": "Airplane Mode",
 "type": "Workspace"
}
